dgl/__init__.py
dgl/_api_internal.py
dgl/_sparse_ops.py
dgl/base.py
dgl/batch.py
dgl/container.py
dgl/convert.py
dgl/core.py
dgl/dgl.dll
dgl/frame.py
dgl/generators.py
dgl/global_config.py
dgl/graph_index.py
dgl/heterograph.py
dgl/heterograph_index.py
dgl/homophily.py
dgl/init.py
dgl/label_informativeness.py
dgl/logging.py
dgl/merge.py
dgl/ndarray.py
dgl/partition.py
dgl/propagate.py
dgl/random.py
dgl/readout.py
dgl/subgraph.py
dgl/traversal.py
dgl/udf.py
dgl/view.py
dgl/_ffi/__init__.py
dgl/_ffi/base.py
dgl/_ffi/capi.py
dgl/_ffi/function.py
dgl/_ffi/libinfo.py
dgl/_ffi/ndarray.py
dgl/_ffi/object.py
dgl/_ffi/object_generic.py
dgl/_ffi/runtime_ctypes.py
dgl/_ffi/streams.py
dgl/_ffi/_ctypes/__init__.py
dgl/_ffi/_ctypes/function.py
dgl/_ffi/_ctypes/ndarray.py
dgl/_ffi/_ctypes/object.py
dgl/_ffi/_ctypes/types.py
dgl/_ffi/_cy2/__init__.py
dgl/_ffi/_cy3/__init__.py
dgl/backend/__init__.py
dgl/backend/backend.py
dgl/backend/set_default_backend.py
dgl/backend/mxnet/__init__.py
dgl/backend/mxnet/sparse.py
dgl/backend/mxnet/sparse_optim.py
dgl/backend/mxnet/tensor.py
dgl/backend/pytorch/__init__.py
dgl/backend/pytorch/sparse.py
dgl/backend/pytorch/tensor.py
dgl/backend/tensorflow/__init__.py
dgl/backend/tensorflow/sparse.py
dgl/backend/tensorflow/sparse_optim.py
dgl/backend/tensorflow/tensor.py
dgl/cuda/__init__.py
dgl/cuda/gpu_cache.py
dgl/cuda/nccl.py
dgl/data/__init__.py
dgl/data/actor.py
dgl/data/adapter.py
dgl/data/bitcoinotc.py
dgl/data/citation_graph.py
dgl/data/cluster.py
dgl/data/csv_dataset.py
dgl/data/csv_dataset_base.py
dgl/data/dgl_dataset.py
dgl/data/fakenews.py
dgl/data/flickr.py
dgl/data/fraud.py
dgl/data/gdelt.py
dgl/data/geom_gcn.py
dgl/data/gindt.py
dgl/data/gnn_benchmark.py
dgl/data/graph_serialize.py
dgl/data/heterograph_serialize.py
dgl/data/heterophilous_graphs.py
dgl/data/icews18.py
dgl/data/karate.py
dgl/data/knowledge_graph.py
dgl/data/lrgb.py
dgl/data/minigc.py
dgl/data/movielens.py
dgl/data/pattern.py
dgl/data/ppi.py
dgl/data/qm7b.py
dgl-2.2.1.dist-info/METADATA
dgl-2.2.1.dist-info/WHEEL
dgl-2.2.1.dist-info/top_level.txt
dgl-2.2.1.dist-info/RECORD
